fastapi_request_context/__init__.py
fastapi_request_context/aiter.py
fastapi_request_context/config.py
fastapi_request_context/context.py
fastapi_request_context/fields.py
fastapi_request_context/middleware.py
fastapi_request_context/py.typed
fastapi_request_context/types.py
fastapi_request_context/validation.py
fastapi_request_context/adapters/__init__.py
fastapi_request_context/adapters/base.py
fastapi_request_context/adapters/context_logging.py
fastapi_request_context/adapters/contextvars.py
fastapi_request_context/contrib/__init__.py
fastapi_request_context/contrib/taskiq/__init__.py
fastapi_request_context/contrib/taskiq/middleware.py
fastapi_request_context/formatters/__init__.py
fastapi_request_context/formatters/json.py
fastapi_request_context/formatters/simple.py
fastapi_request_context-1.4.0.dist-info/METADATA
fastapi_request_context-1.4.0.dist-info/WHEEL
fastapi_request_context-1.4.0.dist-info/licenses/LICENSE
fastapi_request_context-1.4.0.dist-info/RECORD
