Metadata-Version: 2.4
Name: fastapi-request-context
Version: 1.4.0
Summary: FastAPI middleware for request ID tracking, correlation IDs, and extensible request context with logging integration
Project-URL: Homepage, https://github.com/ADR-007/fastapi-request-context
Project-URL: Repository, https://github.com/ADR-007/fastapi-request-context
Project-URL: Issues, https://github.com/ADR-007/fastapi-request-context/issues
Author-email: Adrian Dankiv <adr-007@ukr.net>
License: MIT
License-File: LICENSE
Keywords: correlation-id,fastapi,logging,middleware,request-context,request-id,tracing
Classifier: Development Status :: 4 - Beta
Classifier: Framework :: FastAPI
Classifier: Intended Audience :: Developers
Classifier: License :: OSI Approved :: MIT License
Classifier: Operating System :: OS Independent
Classifier: Programming Language :: Python :: 3
Classifier: Programming Language :: Python :: 3.12
Classifier: Programming Language :: Python :: 3.13
Classifier: Programming Language :: Python :: 3.14
Classifier: Topic :: Internet :: WWW/HTTP :: WSGI :: Middleware
Classifier: Topic :: Software Development :: Libraries :: Python Modules
Classifier: Typing :: Typed
Requires-Python: >=3.12
Requires-Dist: fastapi>=0.100.0
Provides-Extra: all
Requires-Dist: context-logging>=0.7.0; extra == 'all'
Requires-Dist: python-json-logger>=2.0.0; extra == 'all'
Requires-Dist: taskiq>=0.11.0; extra == 'all'
Provides-Extra: build
Requires-Dist: uv>=0.9.0; extra == 'build'
Provides-Extra: context-logging
Requires-Dist: context-logging>=0.7.0; extra == 'context-logging'
Provides-Extra: json-formatter
Requires-Dist: python-json-logger>=2.0.0; extra == 'json-formatter'
Provides-Extra: taskiq
Requires-Dist: taskiq>=0.11.0; extra == 'taskiq'
